contextforce_sdk/__init__.py
contextforce_sdk/main.py
contextforce_sdk-0.2.7.dist-info/LICENSE
contextforce_sdk-0.2.7.dist-info/METADATA
contextforce_sdk-0.2.7.dist-info/WHEEL
contextforce_sdk-0.2.7.dist-info/RECORD
