Metadata-Version: 2.1
Name: contextforce-sdk
Version: 0.2.7
Summary: 
Author: ray
Author-email: ray@contexforce.com
Requires-Python: >=3.12,<4.0
Classifier: Programming Language :: Python :: 3
Classifier: Programming Language :: Python :: 3.12
Requires-Dist: pytest (>=8.3.2,<9.0.0)
Requires-Dist: setuptools (>=72.1.0,<73.0.0)
Requires-Dist: twine (>=5.1.1,<6.0.0)
Requires-Dist: wheel (>=0.44.0,<0.45.0)
